<?xml version="1.0" encoding="UTF-8" standalone="yes" ?>
<!DOCTYPE boost_serialization>
<boost_serialization signature="serialization::archive" version="12">
<lars_model class_id="0" tracking_level="0" version="0">
	<matGramInternal class_id="1" tracking_level="1" version="0" object_id="_0">
		<n_rows>29</n_rows>
		<n_cols>29</n_cols>
		<n_elem>841</n_elem>
		<vec_state>0</vec_state>
		<item>1.16480755434800032e+00</item>
		<item>7.30630872626999883e-01</item>
		<item>1.77485299443899969e+00</item>
		<item>9.88700084389999789e-01</item>
		<item>-1.01182774169388563e+03</item>
		<item>1.03449474301661013e+02</item>
		<item>-3.01627793475900097e+00</item>
		<item>2.08143135723539956e+01</item>
		<item>9.58294217051000263e-01</item>
		<item>6.19405776926499740e+00</item>
		<item>1.01985347970700024e+00</item>
		<item>2.90496319993500141e+00</item>
		<item>1.06495663005399943e+00</item>
		<item>1.82473633752799902e+00</item>
		<item>1.38455718370900049e+00</item>
		<item>1.44810961419400019e+00</item>
		<item>3.29212862965000130e-01</item>
		<item>4.88906619400000103e-03</item>
		<item>4.11072404799999944e-03</item>
		<item>4.30870440100000057e-03</item>
		<item>4.23872121399999739e-03</item>
		<item>3.87210628900000117e-03</item>
		<item>4.46141932599999728e-03</item>
		<item>4.03634493699999916e-03</item>
		<item>4.61983661999999969e-03</item>
		<item>3.85033549599999919e-03</item>
		<item>4.23290932700000084e-03</item>
		<item>4.66052715499999659e-03</item>
		<item>4.09162268699999991e-03</item>
		<item>7.30630872626999883e-01</item>
		<item>5.05049996536999890e-01</item>
		<item>1.22644676813100006e+00</item>
		<item>6.52232754361000366e-01</item>
		<item>-6.55633155456311897e+02</item>
		<item>7.10886597933420319e+01</item>
		<item>-5.34976415087699753e+00</item>
		<item>1.39814308284179987e+01</item>
		<item>-4.18635471255999536e-01</item>
		<item>3.71034954961099839e+00</item>
		<item>2.42418306366999653e-01</item>
		<item>1.70518504215199984e+00</item>
		<item>2.51049436095999889e-01</item>
		<item>8.95575966133000279e-01</item>
		<item>5.62420769990999769e-01</item>
		<item>7.45300896882999830e-01</item>
		<item>-8.49007172059999538e-02</item>
		<item>2.99798791500000082e-03</item>
		<item>2.51208166200000147e-03</item>
		<item>2.67711296300000064e-03</item>
		<item>2.56611985600000130e-03</item>
		<item>2.33789340500000116e-03</item>
		<item>2.72617486800000135e-03</item>
		<item>2.36204506700000115e-03</item>
		<item>2.84178982099999970e-03</item>
		<item>2.31634098399999874e-03</item>
		<item>2.61585247899999993e-03</item>
		<item>2.85644154499999905e-03</item>
		<item>2.45323906599999916e-03</item>
		<item>1.77485299443899969e+00</item>
		<item>1.22644676813100006e+00</item>
		<item>3.29822425680899922e+00</item>
		<item>1.46312693813199957e+00</item>
		<item>-1.45032794510549979e+03</item>
		<item>1.47020549522225053e+02</item>
		<item>-1.05968850105139989e+01</item>
		<item>3.17945008382459946e+01</item>
		<item>-3.84027124448999779e-01</item>
		<item>8.37696417286000283e+00</item>
		<item>7.94138741066999221e-01</item>
		<item>3.94060478420600013e+00</item>
		<item>8.87872658767999479e-01</item>
		<item>2.16032892547199928e+00</item>
		<item>1.89883334921699931e+00</item>
		<item>1.54603812473200053e+00</item>
		<item>-1.53744144487000023e-01</item>
		<item>7.38972471199999918e-03</item>
		<item>6.25525829800000106e-03</item>
		<item>6.58042914599999990e-03</item>
		<item>6.20394904500000052e-03</item>
		<item>5.62851062500000290e-03</item>
		<item>6.44554810300000062e-03</item>
		<item>5.60590332099999977e-03</item>
		<item>7.03709345999999937e-03</item>
		<item>5.62880795800000007e-03</item>
		<item>6.65230058299999972e-03</item>
		<item>7.13465684300000104e-03</item>
		<item>6.04145590799999750e-03</item>
		<item>9.88700084389999789e-01</item>
		<item>6.52232754361000366e-01</item>
		<item>1.46312693813199957e+00</item>
		<item>1.67582181418000031e+00</item>
		<item>-1.18619615057846522e+03</item>
		<item>1.50375557216013988e+02</item>
		<item>-1.03942414337870073e+01</item>
		<item>2.67584363924799931e+01</item>
		<item>1.20916604548000017e+00</item>
		<item>7.20493683054400069e+00</item>
		<item>9.02230574906999427e-01</item>
		<item>3.30234166490300129e+00</item>
		<item>-1.15859362000999222e-01</item>
		<item>2.72470785288499862e+00</item>
		<item>5.53413501659999918e-01</item>
		<item>1.40038678006600015e+00</item>
		<item>1.23353410860000137e-01</item>
		<item>5.09539436699999945e-03</item>
		<item>4.34057625200000123e-03</item>
		<item>4.59849738799999845e-03</item>
		<item>5.07839445300000206e-03</item>
		<item>4.63517678900000202e-03</item>
		<item>5.34133205200000051e-03</item>
		<item>4.62783544599999937e-03</item>
		<item>5.31754314200000126e-03</item>
		<item>4.43267671799999971e-03</item>
		<item>4.58177043900000192e-03</item>
		<item>5.42138455099999781e-03</item>
		<item>4.54348216499999950e-03</item>
		<item>-1.01182774169388563e+03</item>
		<item>-6.55633155456311897e+02</item>
		<item>-1.45032794510549979e+03</item>
		<item>-1.18619615057846522e+03</item>
		<item>1.20813456146548828e+06</item>
		<item>-1.43778889185883862e+05</item>
		<item>5.44272725210331555e+03</item>
		<item>-2.64970199032414421e+04</item>
		<item>-1.59287296161365407e+03</item>
		<item>-8.17759175822258112e+03</item>
		<item>-1.16387043838461955e+03</item>
		<item>-3.72403301342160285e+03</item>
		<item>-8.08430277257450484e+02</item>
		<item>-2.48774188001704442e+03</item>
		<item>-9.94291319225817233e+02</item>
		<item>-1.64586213135253593e+03</item>
		<item>-3.51995100284726334e+02</item>
		<item>-4.68578878483400096e+00</item>
		<item>-3.98520501323000165e+00</item>
		<item>-4.19290987001800008e+00</item>
		<item>-4.27633249614100119e+00</item>
		<item>-3.92990097776400038e+00</item>
		<item>-4.63315104319200444e+00</item>
		<item>-4.03481070234600114e+00</item>
		<item>-4.61293661399899957e+00</item>
		<item>-3.87763167648699980e+00</item>
		<item>-4.09339615812300028e+00</item>
		<item>-4.68593341291900245e+00</item>
		<item>-3.94250986077500087e+00</item>
		<item>1.03449474301661013e+02</item>
		<item>7.10886597933420319e+01</item>
		<item>1.47020549522225053e+02</item>
		<item>1.50375557216013988e+02</item>
		<item>-1.43778889185883862e+05</item>
		<item>2.00947035657069464e+04</item>
		<item>-1.53442561468797521e+03</item>
		<item>3.20362023768924018e+03</item>
		<item>3.71776605216791296e+01</item>
		<item>8.24302706123001826e+02</item>
		<item>5.88646850495989824e+01</item>
		<item>3.80028578757560922e+02</item>
		<item>-6.48570882777829354e+01</item>
		<item>2.67650426047644032e+02</item>
		<item>1.69875480773780083e+01</item>
		<item>1.04949039189331984e+02</item>
		<item>1.22353906966150010e+01</item>
		<item>4.99803144655999954e-01</item>
		<item>4.24506617785000040e-01</item>
		<item>4.52164354623000031e-01</item>
		<item>4.60262531404000141e-01</item>
		<item>4.15526219248999906e-01</item>
		<item>4.99780458631000402e-01</item>
		<item>4.24700247670999897e-01</item>
		<item>4.98512514045999944e-01</item>
		<item>4.12283004574000023e-01</item>
		<item>4.32799959374999932e-01</item>
		<item>4.98572743431999865e-01</item>
		<item>4.11413016283999955e-01</item>
		<item>-3.01627793475900097e+00</item>
		<item>-5.34976415087699753e+00</item>
		<item>-1.05968850105139989e+01</item>
		<item>-1.03942414337870073e+01</item>
		<item>5.44272725210331555e+03</item>
		<item>-1.53442561468797521e+03</item>
		<item>1.02097480390537385e+03</item>
		<item>-2.35492828352434003e+02</item>
		<item>1.38948635266426010e+02</item>
		<item>3.46556405947940078e+01</item>
		<item>2.37515484362149927e+01</item>
		<item>7.03225061492200076e+00</item>
		<item>8.46478628553889791e+01</item>
		<item>8.51556716842001293e-01</item>
		<item>3.34649356484450067e+01</item>
		<item>2.17783063940900021e+01</item>
		<item>2.12319299247409958e+01</item>
		<item>-9.73563177299999888e-03</item>
		<item>-2.68088616000000234e-03</item>
		<item>-6.05364865400000434e-03</item>
		<item>-5.28680647700000873e-03</item>
		<item>8.84169648999993257e-04</item>
		<item>-7.99464645299999450e-03</item>
		<item>-2.51029851499999729e-03</item>
		<item>-1.37832452139999909e-02</item>
		<item>-5.01743981699999744e-03</item>
		<item>-2.68555897999999457e-03</item>
		<item>-4.51115781799999675e-03</item>
		<item>7.23399731300000161e-03</item>
		<item>2.08143135723539956e+01</item>
		<item>1.39814308284179987e+01</item>
		<item>3.17945008382459946e+01</item>
		<item>2.67584363924799931e+01</item>
		<item>-2.64970199032414421e+04</item>
		<item>3.20362023768924018e+03</item>
		<item>-2.35492828352434003e+02</item>
		<item>9.08209850079490025e+02</item>
		<item>-1.90596360801300690e+00</item>
		<item>1.80560946844016001e+02</item>
		<item>3.83186143371930115e+01</item>
		<item>9.28696056450849881e+01</item>
		<item>2.18438811819639938e+01</item>
		<item>5.19491315264660116e+01</item>
		<item>2.42604004283969914e+01</item>
		<item>3.81595143829850088e+01</item>
		<item>-1.02563627339400232e+00</item>
		<item>9.89711219880000104e-02</item>
		<item>8.48824976070000209e-02</item>
		<item>8.50849292820000103e-02</item>
		<item>8.73304155549999295e-02</item>
		<item>8.25818268780000031e-02</item>
		<item>9.92689469750000220e-02</item>
		<item>8.50521288990000457e-02</item>
		<item>1.02039432878999997e-01</item>
		<item>8.49938994300000472e-02</item>
		<item>8.80851403409999983e-02</item>
		<item>1.01573241455000046e-01</item>
		<item>8.09626728110000027e-02</item>
		<item>9.58294217051000263e-01</item>
		<item>-4.18635471255999536e-01</item>
		<item>-3.84027124448999779e-01</item>
		<item>1.20916604548000017e+00</item>
		<item>-1.59287296161365407e+03</item>
		<item>3.71776605216791296e+01</item>
		<item>1.38948635266426010e+02</item>
		<item>-1.90596360801300690e+00</item>
		<item>2.20530672436095131e+02</item>
		<item>1.51434373734750025e+01</item>
		<item>4.49939202395840212e+01</item>
		<item>6.45344425343000250e+00</item>
		<item>2.84802563035600098e+00</item>
		<item>2.90472877627050075e+01</item>
		<item>1.89687819812320058e+01</item>
		<item>1.17766121825170043e+01</item>
		<item>2.73771868223640027e+01</item>
		<item>1.17870824720000024e-02</item>
		<item>1.52885526399999909e-02</item>
		<item>1.23079593919999987e-02</item>
		<item>1.38914815239999934e-02</item>
		<item>1.17891436859999948e-02</item>
		<item>1.32901933680000008e-02</item>
		<item>1.46465702210000024e-02</item>
		<item>1.30032025750000044e-02</item>
		<item>1.37666367439999958e-02</item>
		<item>1.37754504399999964e-02</item>
		<item>1.75107220890000012e-02</item>
		<item>1.19812249469999979e-02</item>
		<item>6.19405776926499740e+00</item>
		<item>3.71034954961099839e+00</item>
		<item>8.37696417286000283e+00</item>
		<item>7.20493683054400069e+00</item>
		<item>-8.17759175822258112e+03</item>
		<item>8.24302706123001826e+02</item>
		<item>3.46556405947940078e+01</item>
		<item>1.80560946844016001e+02</item>
		<item>1.51434373734750025e+01</item>
		<item>1.92140300843709952e+02</item>
		<item>9.05774156325999868e+00</item>
		<item>3.22190518869660139e+01</item>
		<item>2.24965926528620024e+01</item>
		<item>9.80289502714500749e+00</item>
		<item>1.88288769050969975e+01</item>
		<item>1.92213805652080048e+01</item>
		<item>-4.01415119385900265e+00</item>
		<item>3.23188110369999893e-02</item>
		<item>2.86546059889999996e-02</item>
		<item>2.91176652080000035e-02</item>
		<item>2.96246549359999931e-02</item>
		<item>2.89484795230000105e-02</item>
		<item>3.52335785349999903e-02</item>
		<item>2.81747831979999863e-02</item>
		<item>3.09659552619999945e-02</item>
		<item>2.70784875570000069e-02</item>
		<item>2.95437481129999964e-02</item>
		<item>3.58478626050000096e-02</item>
		<item>2.91670845259999999e-02</item>
		<item>1.01985347970700024e+00</item>
		<item>2.42418306366999653e-01</item>
		<item>7.94138741066999221e-01</item>
		<item>9.02230574906999427e-01</item>
		<item>-1.16387043838461955e+03</item>
		<item>5.88646850495989824e+01</item>
		<item>2.37515484362149927e+01</item>
		<item>3.83186143371930115e+01</item>
		<item>4.49939202395840212e+01</item>
		<item>9.05774156325999868e+00</item>
		<item>1.16894867338741051e+02</item>
		<item>1.51049075004220015e+01</item>
		<item>8.07006493095800259e+00</item>
		<item>8.72561420042300284e+00</item>
		<item>7.83530435786899737e+00</item>
		<item>1.51357653555520031e+01</item>
		<item>1.47641024194200057e+01</item>
		<item>1.13097625340000014e-02</item>
		<item>1.00903121720000016e-02</item>
		<item>9.38529133399999826e-03</item>
		<item>1.12971776600000011e-02</item>
		<item>1.07138837220000019e-02</item>
		<item>1.19362632740000005e-02</item>
		<item>1.04623765090000043e-02</item>
		<item>8.76907032700000380e-03</item>
		<item>8.67964195899999409e-03</item>
		<item>9.54458127300000098e-03</item>
		<item>1.29995548950000029e-02</item>
		<item>1.04893176760000040e-02</item>
		<item>2.90496319993500141e+00</item>
		<item>1.70518504215199984e+00</item>
		<item>3.94060478420600013e+00</item>
		<item>3.30234166490300129e+00</item>
		<item>-3.72403301342160285e+03</item>
		<item>3.80028578757560922e+02</item>
		<item>7.03225061492200076e+00</item>
		<item>9.28696056450849881e+01</item>
		<item>6.45344425343000250e+00</item>
		<item>3.22190518869660139e+01</item>
		<item>1.51049075004220015e+01</item>
		<item>9.48893982939069645e+01</item>
		<item>1.97241330097260033e+01</item>
		<item>1.32083728961340050e+01</item>
		<item>5.32709522989399975e+00</item>
		<item>1.05104763934390011e+01</item>
		<item>1.39161069294899509e+00</item>
		<item>1.75654447510000047e-02</item>
		<item>1.70660908189999988e-02</item>
		<item>1.35633040229999960e-02</item>
		<item>1.44879964339999969e-02</item>
		<item>1.56792176340000006e-02</item>
		<item>1.65091594039999956e-02</item>
		<item>1.42294235159999959e-02</item>
		<item>1.47019636059999900e-02</item>
		<item>1.42792136080000000e-02</item>
		<item>1.62464820069999974e-02</item>
		<item>1.93963168029999931e-02</item>
		<item>1.47791618410000013e-02</item>
		<item>1.06495663005399943e+00</item>
		<item>2.51049436095999889e-01</item>
		<item>8.87872658767999479e-01</item>
		<item>-1.15859362000999222e-01</item>
		<item>-8.08430277257450484e+02</item>
		<item>-6.48570882777829354e+01</item>
		<item>8.46478628553889791e+01</item>
		<item>2.18438811819639938e+01</item>
		<item>2.84802563035600098e+00</item>
		<item>2.24965926528620024e+01</item>
		<item>8.07006493095800259e+00</item>
		<item>1.97241330097260033e+01</item>
		<item>8.97264982777669786e+01</item>
		<item>1.52237357466569989e+01</item>
		<item>1.23247008562699953e+01</item>
		<item>5.26172492036999540e+00</item>
		<item>-3.10338751974199933e+00</item>
		<item>1.06197516879999974e-02</item>
		<item>9.86383766999999675e-03</item>
		<item>8.21240976700000035e-03</item>
		<item>6.71651909300000072e-03</item>
		<item>6.65363531900000065e-03</item>
		<item>5.41512283599999977e-03</item>
		<item>6.88559223100000325e-03</item>
		<item>8.60662234699999772e-03</item>
		<item>8.34944312700000232e-03</item>
		<item>9.69353430000000071e-03</item>
		<item>9.07165697399999957e-03</item>
		<item>8.33399339699999672e-03</item>
		<item>1.82473633752799902e+00</item>
		<item>8.95575966133000279e-01</item>
		<item>2.16032892547199928e+00</item>
		<item>2.72470785288499862e+00</item>
		<item>-2.48774188001704442e+03</item>
		<item>2.67650426047644032e+02</item>
		<item>8.51556716842001293e-01</item>
		<item>5.19491315264660116e+01</item>
		<item>2.90472877627050075e+01</item>
		<item>9.80289502714500749e+00</item>
		<item>8.72561420042300284e+00</item>
		<item>1.32083728961340050e+01</item>
		<item>1.52237357466569989e+01</item>
		<item>7.31798455298129937e+01</item>
		<item>1.13285675166119937e+01</item>
		<item>2.34971075324599976e+00</item>
		<item>9.40829204794799878e+00</item>
		<item>1.02946406430000012e-02</item>
		<item>9.13959700700000058e-03</item>
		<item>9.54376996299999628e-03</item>
		<item>1.15689851500000024e-02</item>
		<item>9.47957254500000207e-03</item>
		<item>1.14951061050000015e-02</item>
		<item>1.05666060540000016e-02</item>
		<item>1.23173550630000031e-02</item>
		<item>1.07076350080000035e-02</item>
		<item>1.05944640739999967e-02</item>
		<item>1.29277901129999928e-02</item>
		<item>9.17966376500000195e-03</item>
		<item>1.38455718370900049e+00</item>
		<item>5.62420769990999769e-01</item>
		<item>1.89883334921699931e+00</item>
		<item>5.53413501659999918e-01</item>
		<item>-9.94291319225817233e+02</item>
		<item>1.69875480773780083e+01</item>
		<item>3.34649356484450067e+01</item>
		<item>2.42604004283969914e+01</item>
		<item>1.89687819812320058e+01</item>
		<item>1.88288769050969975e+01</item>
		<item>7.83530435786899737e+00</item>
		<item>5.32709522989399975e+00</item>
		<item>1.23247008562699953e+01</item>
		<item>1.13285675166119937e+01</item>
		<item>4.61488851402919948e+01</item>
		<item>1.39284066320570084e+01</item>
		<item>9.03274274315599612e+00</item>
		<item>8.76005646499999728e-03</item>
		<item>7.76582619400000007e-03</item>
		<item>7.32119740800000075e-03</item>
		<item>8.29335980400000561e-03</item>
		<item>6.84274601399999759e-03</item>
		<item>1.07499596310000022e-02</item>
		<item>8.69955272899999854e-03</item>
		<item>1.02131015349999996e-02</item>
		<item>8.95885203399999878e-03</item>
		<item>7.33966722400000021e-03</item>
		<item>9.21167835400000037e-03</item>
		<item>6.33760132100000088e-03</item>
		<item>1.44810961419400019e+00</item>
		<item>7.45300896882999830e-01</item>
		<item>1.54603812473200053e+00</item>
		<item>1.40038678006600015e+00</item>
		<item>-1.64586213135253593e+03</item>
		<item>1.04949039189331984e+02</item>
		<item>2.17783063940900021e+01</item>
		<item>3.81595143829850088e+01</item>
		<item>1.17766121825170043e+01</item>
		<item>1.92213805652080048e+01</item>
		<item>1.51357653555520031e+01</item>
		<item>1.05104763934390011e+01</item>
		<item>5.26172492036999540e+00</item>
		<item>2.34971075324599976e+00</item>
		<item>1.39284066320570084e+01</item>
		<item>4.51841755430479850e+01</item>
		<item>1.28557662042949996e+01</item>
		<item>8.15535548200000543e-03</item>
		<item>6.45938250699999977e-03</item>
		<item>7.44132833399999832e-03</item>
		<item>9.23652159199999344e-03</item>
		<item>8.78093613299999777e-03</item>
		<item>1.10963326809999981e-02</item>
		<item>9.19758600700000019e-03</item>
		<item>1.03445955049999965e-02</item>
		<item>8.67389914400000343e-03</item>
		<item>6.47920030700000014e-03</item>
		<item>8.90955843100000103e-03</item>
		<item>7.61677140300000277e-03</item>
		<item>3.29212862965000130e-01</item>
		<item>-8.49007172059999538e-02</item>
		<item>-1.53744144487000023e-01</item>
		<item>1.23353410860000137e-01</item>
		<item>-3.51995100284726334e+02</item>
		<item>1.22353906966150010e+01</item>
		<item>2.12319299247409958e+01</item>
		<item>-1.02563627339400232e+00</item>
		<item>2.73771868223640027e+01</item>
		<item>-4.01415119385900265e+00</item>
		<item>1.47641024194200057e+01</item>
		<item>1.39161069294899509e+00</item>
		<item>-3.10338751974199933e+00</item>
		<item>9.40829204794799878e+00</item>
		<item>9.03274274315599612e+00</item>
		<item>1.28557662042949996e+01</item>
		<item>4.69089157921500117e+01</item>
		<item>3.83254668800000293e-03</item>
		<item>2.55968280500000131e-03</item>
		<item>3.33755205300000166e-03</item>
		<item>3.97624364799999998e-03</item>
		<item>3.74424497599999944e-03</item>
		<item>4.58339608900000355e-03</item>
		<item>3.84827851299999763e-03</item>
		<item>2.25544494399999851e-03</item>
		<item>2.35262457899999833e-03</item>
		<item>1.78825660299999890e-03</item>
		<item>3.25759192700000085e-03</item>
		<item>3.70494577800000065e-03</item>
		<item>4.88906619400000103e-03</item>
		<item>2.99798791500000082e-03</item>
		<item>7.38972471199999918e-03</item>
		<item>5.09539436699999945e-03</item>
		<item>-4.68578878483400096e+00</item>
		<item>4.99803144655999954e-01</item>
		<item>-9.73563177299999888e-03</item>
		<item>9.89711219880000104e-02</item>
		<item>1.17870824720000024e-02</item>
		<item>3.23188110369999893e-02</item>
		<item>1.13097625340000014e-02</item>
		<item>1.75654447510000047e-02</item>
		<item>1.06197516879999974e-02</item>
		<item>1.02946406430000012e-02</item>
		<item>8.76005646499999728e-03</item>
		<item>8.15535548200000543e-03</item>
		<item>3.83254668800000293e-03</item>
		<item>6.30237689999999456e-05</item>
		<item>4.37515610000000098e-05</item>
		<item>4.50175440000000009e-05</item>
		<item>4.28129159999999815e-05</item>
		<item>3.88573809999999929e-05</item>
		<item>4.60368889999999894e-05</item>
		<item>3.89670760000000163e-05</item>
		<item>5.22672700000000184e-05</item>
		<item>3.92410310000000176e-05</item>
		<item>3.89249680000000169e-05</item>
		<item>4.59001899999999906e-05</item>
		<item>4.20563500000000027e-05</item>
		<item>4.11072404799999944e-03</item>
		<item>2.51208166200000147e-03</item>
		<item>6.25525829800000106e-03</item>
		<item>4.34057625200000123e-03</item>
		<item>-3.98520501323000165e+00</item>
		<item>4.24506617785000040e-01</item>
		<item>-2.68088616000000234e-03</item>
		<item>8.48824976070000209e-02</item>
		<item>1.52885526399999909e-02</item>
		<item>2.86546059889999996e-02</item>
		<item>1.00903121720000016e-02</item>
		<item>1.70660908189999988e-02</item>
		<item>9.86383766999999675e-03</item>
		<item>9.13959700700000058e-03</item>
		<item>7.76582619400000007e-03</item>
		<item>6.45938250699999977e-03</item>
		<item>2.55968280500000131e-03</item>
		<item>4.37515610000000098e-05</item>
		<item>4.18378560000000213e-05</item>
		<item>3.87355140000000003e-05</item>
		<item>3.40949760000000058e-05</item>
		<item>3.17370449999999942e-05</item>
		<item>3.60369849999999861e-05</item>
		<item>3.47631580000000114e-05</item>
		<item>3.99618160000000114e-05</item>
		<item>3.24351679999999965e-05</item>
		<item>3.39233169999999737e-05</item>
		<item>3.91632200000000062e-05</item>
		<item>3.36487970000000209e-05</item>
		<item>4.30870440100000057e-03</item>
		<item>2.67711296300000064e-03</item>
		<item>6.58042914599999990e-03</item>
		<item>4.59849738799999845e-03</item>
		<item>-4.19290987001800008e+00</item>
		<item>4.52164354623000031e-01</item>
		<item>-6.05364865400000434e-03</item>
		<item>8.50849292820000103e-02</item>
		<item>1.23079593919999987e-02</item>
		<item>2.91176652080000035e-02</item>
		<item>9.38529133399999826e-03</item>
		<item>1.35633040229999960e-02</item>
		<item>8.21240976700000035e-03</item>
		<item>9.54376996299999628e-03</item>
		<item>7.32119740800000075e-03</item>
		<item>7.44132833399999832e-03</item>
		<item>3.33755205300000166e-03</item>
		<item>4.50175440000000009e-05</item>
		<item>3.87355140000000003e-05</item>
		<item>4.93118290000000445e-05</item>
		<item>4.24625109999999988e-05</item>
		<item>3.55412550000000084e-05</item>
		<item>3.97481740000000090e-05</item>
		<item>3.62322329999999920e-05</item>
		<item>4.65183940000000020e-05</item>
		<item>3.39203800000000406e-05</item>
		<item>3.75319279999999819e-05</item>
		<item>4.20960680000000178e-05</item>
		<item>3.58442209999999955e-05</item>
		<item>4.23872121399999739e-03</item>
		<item>2.56611985600000130e-03</item>
		<item>6.20394904500000052e-03</item>
		<item>5.07839445300000206e-03</item>
		<item>-4.27633249614100119e+00</item>
		<item>4.60262531404000141e-01</item>
		<item>-5.28680647700000873e-03</item>
		<item>8.73304155549999295e-02</item>
		<item>1.38914815239999934e-02</item>
		<item>2.96246549359999931e-02</item>
		<item>1.12971776600000011e-02</item>
		<item>1.44879964339999969e-02</item>
		<item>6.71651909300000072e-03</item>
		<item>1.15689851500000024e-02</item>
		<item>8.29335980400000561e-03</item>
		<item>9.23652159199999344e-03</item>
		<item>3.97624364799999998e-03</item>
		<item>4.28129159999999815e-05</item>
		<item>3.40949760000000058e-05</item>
		<item>4.24625109999999988e-05</item>
		<item>5.34996060000000152e-05</item>
		<item>3.94013730000000116e-05</item>
		<item>4.31225930000000274e-05</item>
		<item>3.81154790000000276e-05</item>
		<item>4.51260519999999832e-05</item>
		<item>3.62041069999999868e-05</item>
		<item>3.49852280000000220e-05</item>
		<item>4.39299150000000088e-05</item>
		<item>3.45999180000000167e-05</item>
		<item>3.87210628900000117e-03</item>
		<item>2.33789340500000116e-03</item>
		<item>5.62851062500000290e-03</item>
		<item>4.63517678900000202e-03</item>
		<item>-3.92990097776400038e+00</item>
		<item>4.15526219248999906e-01</item>
		<item>8.84169648999993257e-04</item>
		<item>8.25818268780000031e-02</item>
		<item>1.17891436859999948e-02</item>
		<item>2.89484795230000105e-02</item>
		<item>1.07138837220000019e-02</item>
		<item>1.56792176340000006e-02</item>
		<item>6.65363531900000065e-03</item>
		<item>9.47957254500000207e-03</item>
		<item>6.84274601399999759e-03</item>
		<item>8.78093613299999777e-03</item>
		<item>3.74424497599999944e-03</item>
		<item>3.88573809999999929e-05</item>
		<item>3.17370449999999942e-05</item>
		<item>3.55412550000000084e-05</item>
		<item>3.94013730000000116e-05</item>
		<item>4.33363350000000436e-05</item>
		<item>4.34397269999999702e-05</item>
		<item>3.68225890000000122e-05</item>
		<item>4.07938540000000305e-05</item>
		<item>3.12384420000000242e-05</item>
		<item>3.44902919999999751e-05</item>
		<item>3.97195150000000127e-05</item>
		<item>3.49111630000000314e-05</item>
		<item>4.46141932599999728e-03</item>
		<item>2.72617486800000135e-03</item>
		<item>6.44554810300000062e-03</item>
		<item>5.34133205200000051e-03</item>
		<item>-4.63315104319200444e+00</item>
		<item>4.99780458631000402e-01</item>
		<item>-7.99464645299999450e-03</item>
		<item>9.92689469750000220e-02</item>
		<item>1.32901933680000008e-02</item>
		<item>3.52335785349999903e-02</item>
		<item>1.19362632740000005e-02</item>
		<item>1.65091594039999956e-02</item>
		<item>5.41512283599999977e-03</item>
		<item>1.14951061050000015e-02</item>
		<item>1.07499596310000022e-02</item>
		<item>1.10963326809999981e-02</item>
		<item>4.58339608900000355e-03</item>
		<item>4.60368889999999894e-05</item>
		<item>3.60369849999999861e-05</item>
		<item>3.97481740000000090e-05</item>
		<item>4.31225930000000274e-05</item>
		<item>4.34397269999999702e-05</item>
		<item>5.74878160000000195e-05</item>
		<item>4.36095100000000039e-05</item>
		<item>4.60054790000000011e-05</item>
		<item>3.64915380000000052e-05</item>
		<item>3.81562959999999881e-05</item>
		<item>4.85432869999999909e-05</item>
		<item>3.70454949999999823e-05</item>
		<item>4.03634493699999916e-03</item>
		<item>2.36204506700000115e-03</item>
		<item>5.60590332099999977e-03</item>
		<item>4.62783544599999937e-03</item>
		<item>-4.03481070234600114e+00</item>
		<item>4.24700247670999897e-01</item>
		<item>-2.51029851499999729e-03</item>
		<item>8.50521288990000457e-02</item>
		<item>1.46465702210000024e-02</item>
		<item>2.81747831979999863e-02</item>
		<item>1.04623765090000043e-02</item>
		<item>1.42294235159999959e-02</item>
		<item>6.88559223100000325e-03</item>
		<item>1.05666060540000016e-02</item>
		<item>8.69955272899999854e-03</item>
		<item>9.19758600700000019e-03</item>
		<item>3.84827851299999763e-03</item>
		<item>3.89670760000000163e-05</item>
		<item>3.47631580000000114e-05</item>
		<item>3.62322329999999920e-05</item>
		<item>3.81154790000000276e-05</item>
		<item>3.68225890000000122e-05</item>
		<item>4.36095100000000039e-05</item>
		<item>4.57011980000000169e-05</item>
		<item>4.47110430000000037e-05</item>
		<item>3.48451600000000071e-05</item>
		<item>3.56160140000000042e-05</item>
		<item>4.19493150000000028e-05</item>
		<item>3.43289059999999990e-05</item>
		<item>4.61983661999999969e-03</item>
		<item>2.84178982099999970e-03</item>
		<item>7.03709345999999937e-03</item>
		<item>5.31754314200000126e-03</item>
		<item>-4.61293661399899957e+00</item>
		<item>4.98512514045999944e-01</item>
		<item>-1.37832452139999909e-02</item>
		<item>1.02039432878999997e-01</item>
		<item>1.30032025750000044e-02</item>
		<item>3.09659552619999945e-02</item>
		<item>8.76907032700000380e-03</item>
		<item>1.47019636059999900e-02</item>
		<item>8.60662234699999772e-03</item>
		<item>1.23173550630000031e-02</item>
		<item>1.02131015349999996e-02</item>
		<item>1.03445955049999965e-02</item>
		<item>2.25544494399999851e-03</item>
		<item>5.22672700000000184e-05</item>
		<item>3.99618160000000114e-05</item>
		<item>4.65183940000000020e-05</item>
		<item>4.51260519999999832e-05</item>
		<item>4.07938540000000305e-05</item>
		<item>4.60054790000000011e-05</item>
		<item>4.47110430000000037e-05</item>
		<item>6.46667890000000530e-05</item>
		<item>4.55324840000000011e-05</item>
		<item>4.26680940000000094e-05</item>
		<item>4.77988390000000208e-05</item>
		<item>4.11413969999999905e-05</item>
		<item>3.85033549599999919e-03</item>
		<item>2.31634098399999874e-03</item>
		<item>5.62880795800000007e-03</item>
		<item>4.43267671799999971e-03</item>
		<item>-3.87763167648699980e+00</item>
		<item>4.12283004574000023e-01</item>
		<item>-5.01743981699999744e-03</item>
		<item>8.49938994300000472e-02</item>
		<item>1.37666367439999958e-02</item>
		<item>2.70784875570000069e-02</item>
		<item>8.67964195899999409e-03</item>
		<item>1.42792136080000000e-02</item>
		<item>8.34944312700000232e-03</item>
		<item>1.07076350080000035e-02</item>
		<item>8.95885203399999878e-03</item>
		<item>8.67389914400000343e-03</item>
		<item>2.35262457899999833e-03</item>
		<item>3.92410310000000176e-05</item>
		<item>3.24351679999999965e-05</item>
		<item>3.39203800000000406e-05</item>
		<item>3.62041069999999868e-05</item>
		<item>3.12384420000000242e-05</item>
		<item>3.64915380000000052e-05</item>
		<item>3.48451600000000071e-05</item>
		<item>4.55324840000000011e-05</item>
		<item>4.27678370000000223e-05</item>
		<item>3.59956230000000281e-05</item>
		<item>3.91022679999999923e-05</item>
		<item>3.19293840000000093e-05</item>
		<item>4.23290932700000084e-03</item>
		<item>2.61585247899999993e-03</item>
		<item>6.65230058299999972e-03</item>
		<item>4.58177043900000192e-03</item>
		<item>-4.09339615812300028e+00</item>
		<item>4.32799959374999932e-01</item>
		<item>-2.68555897999999457e-03</item>
		<item>8.80851403409999983e-02</item>
		<item>1.37754504399999964e-02</item>
		<item>2.95437481129999964e-02</item>
		<item>9.54458127300000098e-03</item>
		<item>1.62464820069999974e-02</item>
		<item>9.69353430000000071e-03</item>
		<item>1.05944640739999967e-02</item>
		<item>7.33966722400000021e-03</item>
		<item>6.47920030700000014e-03</item>
		<item>1.78825660299999890e-03</item>
		<item>3.89249680000000169e-05</item>
		<item>3.39233169999999737e-05</item>
		<item>3.75319279999999819e-05</item>
		<item>3.49852280000000220e-05</item>
		<item>3.44902919999999751e-05</item>
		<item>3.81562959999999881e-05</item>
		<item>3.56160140000000042e-05</item>
		<item>4.26680940000000094e-05</item>
		<item>3.59956230000000281e-05</item>
		<item>4.42505200000000210e-05</item>
		<item>4.53295509999999930e-05</item>
		<item>3.53269249999999836e-05</item>
		<item>4.66052715499999659e-03</item>
		<item>2.85644154499999905e-03</item>
		<item>7.13465684300000104e-03</item>
		<item>5.42138455099999781e-03</item>
		<item>-4.68593341291900245e+00</item>
		<item>4.98572743431999865e-01</item>
		<item>-4.51115781799999675e-03</item>
		<item>1.01573241455000046e-01</item>
		<item>1.75107220890000012e-02</item>
		<item>3.58478626050000096e-02</item>
		<item>1.29995548950000029e-02</item>
		<item>1.93963168029999931e-02</item>
		<item>9.07165697399999957e-03</item>
		<item>1.29277901129999928e-02</item>
		<item>9.21167835400000037e-03</item>
		<item>8.90955843100000103e-03</item>
		<item>3.25759192700000085e-03</item>
		<item>4.59001899999999906e-05</item>
		<item>3.91632200000000062e-05</item>
		<item>4.20960680000000178e-05</item>
		<item>4.39299150000000088e-05</item>
		<item>3.97195150000000127e-05</item>
		<item>4.85432869999999909e-05</item>
		<item>4.19493150000000028e-05</item>
		<item>4.77988390000000208e-05</item>
		<item>3.91022679999999923e-05</item>
		<item>4.53295509999999930e-05</item>
		<item>6.65609300000000377e-05</item>
		<item>4.34613229999999929e-05</item>
		<item>4.09162268699999991e-03</item>
		<item>2.45323906599999916e-03</item>
		<item>6.04145590799999750e-03</item>
		<item>4.54348216499999950e-03</item>
		<item>-3.94250986077500087e+00</item>
		<item>4.11413016283999955e-01</item>
		<item>7.23399731300000161e-03</item>
		<item>8.09626728110000027e-02</item>
		<item>1.19812249469999979e-02</item>
		<item>2.91670845259999999e-02</item>
		<item>1.04893176760000040e-02</item>
		<item>1.47791618410000013e-02</item>
		<item>8.33399339699999672e-03</item>
		<item>9.17966376500000195e-03</item>
		<item>6.33760132100000088e-03</item>
		<item>7.61677140300000277e-03</item>
		<item>3.70494577800000065e-03</item>
		<item>4.20563500000000027e-05</item>
		<item>3.36487970000000209e-05</item>
		<item>3.58442209999999955e-05</item>
		<item>3.45999180000000167e-05</item>
		<item>3.49111630000000314e-05</item>
		<item>3.70454949999999823e-05</item>
		<item>3.43289059999999990e-05</item>
		<item>4.11413969999999905e-05</item>
		<item>3.19293840000000093e-05</item>
		<item>3.53269249999999836e-05</item>
		<item>4.34613229999999929e-05</item>
		<item>3.98136510000000210e-05</item>
	</matGramInternal>
	<matUtriCholFactor object_id="_1">
		<n_rows>0</n_rows>
		<n_cols>0</n_cols>
		<n_elem>0</n_elem>
		<vec_state>0</vec_state>
	</matUtriCholFactor>
	<useCholesky>0</useCholesky>
	<lasso>0</lasso>
	<lambda1>0.00000000000000000e+00</lambda1>
	<elasticNet>0</elasticNet>
	<lambda2>0.00000000000000000e+00</lambda2>
	<tolerance>9.99999999999999979e-17</tolerance>
	<betaPath class_id="2" tracking_level="0" version="0">
		<count>30</count>
		<item_version>0</item_version>
		<item class_id="3" tracking_level="0" version="0">
			<n_rows>29</n_rows>
			<n_cols>1</n_cols>
			<n_elem>29</n_elem>
			<vec_state>1</vec_state>
			<item>0.00000000000000000e+00</item>
			<item>0.00000000000000000e+00</item>
			<item>0.00000000000000000e+00</item>
			<item>0.00000000000000000e+00</item>
			<item>0.00000000000000000e+00</item>
			<item>0.00000000000000000e+00</item>
			<item>0.00000000000000000e+00</item>
			<item>0.00000000000000000e+00</item>
			<item>0.00000000000000000e+00</item>
			<item>0.00000000000000000e+00</item>
			<item>0.00000000000000000e+00</item>
			<item>0.00000000000000000e+00</item>
			<item>0.00000000000000000e+00</item>
			<item>0.00000000000000000e+00</item>
			<item>0.00000000000000000e+00</item>
			<item>0.00000000000000000e+00</item>
			<item>0.00000000000000000e+00</item>
			<item>0.00000000000000000e+00</item>
			<item>0.00000000000000000e+00</item>
			<item>0.00000000000000000e+00</item>
			<item>0.00000000000000000e+00</item>
			<item>0.00000000000000000e+00</item>
			<item>0.00000000000000000e+00</item>
			<item>0.00000000000000000e+00</item>
			<item>0.00000000000000000e+00</item>
			<item>0.00000000000000000e+00</item>
			<item>0.00000000000000000e+00</item>
			<item>0.00000000000000000e+00</item>
			<item>0.00000000000000000e+00</item>
		</item>
		<item>
			<n_rows>29</n_rows>
			<n_cols>1</n_cols>
			<n_elem>29</n_elem>
			<vec_state>1</vec_state>
			<item>0.00000000000000000e+00</item>
			<item>0.00000000000000000e+00</item>
			<item>0.00000000000000000e+00</item>
			<item>0.00000000000000000e+00</item>
			<item>-1.00306333825308902e-01</item>
			<item>0.00000000000000000e+00</item>
			<item>0.00000000000000000e+00</item>
			<item>0.00000000000000000e+00</item>
			<item>0.00000000000000000e+00</item>
			<item>0.00000000000000000e+00</item>
			<item>0.00000000000000000e+00</item>
			<item>0.00000000000000000e+00</item>
			<item>0.00000000000000000e+00</item>
			<item>0.00000000000000000e+00</item>
			<item>0.00000000000000000e+00</item>
			<item>0.00000000000000000e+00</item>
			<item>0.00000000000000000e+00</item>
			<item>0.00000000000000000e+00</item>
			<item>0.00000000000000000e+00</item>
			<item>0.00000000000000000e+00</item>
			<item>0.00000000000000000e+00</item>
			<item>0.00000000000000000e+00</item>
			<item>0.00000000000000000e+00</item>
			<item>0.00000000000000000e+00</item>
			<item>0.00000000000000000e+00</item>
			<item>0.00000000000000000e+00</item>
			<item>0.00000000000000000e+00</item>
			<item>0.00000000000000000e+00</item>
			<item>0.00000000000000000e+00</item>
		</item>
		<item>
			<n_rows>29</n_rows>
			<n_cols>1</n_cols>
			<n_elem>29</n_elem>
			<vec_state>1</vec_state>
			<item>0.00000000000000000e+00</item>
			<item>0.00000000000000000e+00</item>
			<item>0.00000000000000000e+00</item>
			<item>0.00000000000000000e+00</item>
			<item>-1.29008140920637032e-01</item>
			<item>-2.36782256485912085e-01</item>
			<item>0.00000000000000000e+00</item>
			<item>0.00000000000000000e+00</item>
			<item>0.00000000000000000e+00</item>
			<item>0.00000000000000000e+00</item>
			<item>0.00000000000000000e+00</item>
			<item>0.00000000000000000e+00</item>
			<item>0.00000000000000000e+00</item>
			<item>0.00000000000000000e+00</item>
			<item>0.00000000000000000e+00</item>
			<item>0.00000000000000000e+00</item>
			<item>0.00000000000000000e+00</item>
			<item>0.00000000000000000e+00</item>
			<item>0.00000000000000000e+00</item>
			<item>0.00000000000000000e+00</item>
			<item>0.00000000000000000e+00</item>
			<item>0.00000000000000000e+00</item>
			<item>0.00000000000000000e+00</item>
			<item>0.00000000000000000e+00</item>
			<item>0.00000000000000000e+00</item>
			<item>0.00000000000000000e+00</item>
			<item>0.00000000000000000e+00</item>
			<item>0.00000000000000000e+00</item>
			<item>0.00000000000000000e+00</item>
		</item>
		<item>
			<n_rows>29</n_rows>
			<n_cols>1</n_cols>
			<n_elem>29</n_elem>
			<vec_state>1</vec_state>
			<item>0.00000000000000000e+00</item>
			<item>0.00000000000000000e+00</item>
			<item>0.00000000000000000e+00</item>
			<item>0.00000000000000000e+00</item>
			<item>-1.30400841339672252e-01</item>
			<item>-2.49331441255225578e-01</item>
			<item>-2.48911795893195197e-02</item>
			<item>0.00000000000000000e+00</item>
			<item>0.00000000000000000e+00</item>
			<item>0.00000000000000000e+00</item>
			<item>0.00000000000000000e+00</item>
			<item>0.00000000000000000e+00</item>
			<item>0.00000000000000000e+00</item>
			<item>0.00000000000000000e+00</item>
			<item>0.00000000000000000e+00</item>
			<item>0.00000000000000000e+00</item>
			<item>0.00000000000000000e+00</item>
			<item>0.00000000000000000e+00</item>
			<item>0.00000000000000000e+00</item>
			<item>0.00000000000000000e+00</item>
			<item>0.00000000000000000e+00</item>
			<item>0.00000000000000000e+00</item>
			<item>0.00000000000000000e+00</item>
			<item>0.00000000000000000e+00</item>
			<item>0.00000000000000000e+00</item>
			<item>0.00000000000000000e+00</item>
			<item>0.00000000000000000e+00</item>
			<item>0.00000000000000000e+00</item>
			<item>0.00000000000000000e+00</item>
		</item>
		<item>
			<n_rows>29</n_rows>
			<n_cols>1</n_cols>
			<n_elem>29</n_elem>
			<vec_state>1</vec_state>
			<item>0.00000000000000000e+00</item>
			<item>0.00000000000000000e+00</item>
			<item>0.00000000000000000e+00</item>
			<item>0.00000000000000000e+00</item>
			<item>-1.32950237971704077e-01</item>
			<item>-2.62592459050916160e-01</item>
			<item>-5.57085188129561107e-02</item>
			<item>-5.01150900389639165e-02</item>
			<item>0.00000000000000000e+00</item>
			<item>0.00000000000000000e+00</item>
			<item>0.00000000000000000e+00</item>
			<item>0.00000000000000000e+00</item>
			<item>0.00000000000000000e+00</item>
			<item>0.00000000000000000e+00</item>
			<item>0.00000000000000000e+00</item>
			<item>0.00000000000000000e+00</item>
			<item>0.00000000000000000e+00</item>
			<item>0.00000000000000000e+00</item>
			<item>0.00000000000000000e+00</item>
			<item>0.00000000000000000e+00</item>
			<item>0.00000000000000000e+00</item>
			<item>0.00000000000000000e+00</item>
			<item>0.00000000000000000e+00</item>
			<item>0.00000000000000000e+00</item>
			<item>0.00000000000000000e+00</item>
			<item>0.00000000000000000e+00</item>
			<item>0.00000000000000000e+00</item>
			<item>0.00000000000000000e+00</item>
			<item>0.00000000000000000e+00</item>
		</item>
		<item>
			<n_rows>29</n_rows>
			<n_cols>1</n_cols>
			<n_elem>29</n_elem>
			<vec_state>1</vec_state>
			<item>0.00000000000000000e+00</item>
			<item>0.00000000000000000e+00</item>
			<item>0.00000000000000000e+00</item>
			<item>0.00000000000000000e+00</item>
			<item>-1.32979126650245721e-01</item>
			<item>-2.62766449867254059e-01</item>
			<item>-5.61793298452837181e-02</item>
			<item>-5.08461467943683229e-02</item>
			<item>0.00000000000000000e+00</item>
			<item>0.00000000000000000e+00</item>
			<item>0.00000000000000000e+00</item>
			<item>0.00000000000000000e+00</item>
			<item>0.00000000000000000e+00</item>
			<item>2.86182121531462644e-03</item>
			<item>0.00000000000000000e+00</item>
			<item>0.00000000000000000e+00</item>
			<item>0.00000000000000000e+00</item>
			<item>0.00000000000000000e+00</item>
			<item>0.00000000000000000e+00</item>
			<item>0.00000000000000000e+00</item>
			<item>0.00000000000000000e+00</item>
			<item>0.00000000000000000e+00</item>
			<item>0.00000000000000000e+00</item>
			<item>0.00000000000000000e+00</item>
			<item>0.00000000000000000e+00</item>
			<item>0.00000000000000000e+00</item>
			<item>0.00000000000000000e+00</item>
			<item>0.00000000000000000e+00</item>
			<item>0.00000000000000000e+00</item>
		</item>
		<item>
			<n_rows>29</n_rows>
			<n_cols>1</n_cols>
			<n_elem>29</n_elem>
			<vec_state>1</vec_state>
			<item>0.00000000000000000e+00</item>
			<item>0.00000000000000000e+00</item>
			<item>0.00000000000000000e+00</item>
			<item>0.00000000000000000e+00</item>
			<item>-1.33147207707497828e-01</item>
			<item>-2.63408437387850636e-01</item>
			<item>-6.28909386998548064e-02</item>
			<item>-6.11619107736810635e-02</item>
			<item>0.00000000000000000e+00</item>
			<item>0.00000000000000000e+00</item>
			<item>0.00000000000000000e+00</item>
			<item>0.00000000000000000e+00</item>
			<item>0.00000000000000000e+00</item>
			<item>3.29278492970541056e-02</item>
			<item>5.40770023865064509e-02</item>
			<item>0.00000000000000000e+00</item>
			<item>0.00000000000000000e+00</item>
			<item>0.00000000000000000e+00</item>
			<item>0.00000000000000000e+00</item>
			<item>0.00000000000000000e+00</item>
			<item>0.00000000000000000e+00</item>
			<item>0.00000000000000000e+00</item>
			<item>0.00000000000000000e+00</item>
			<item>0.00000000000000000e+00</item>
			<item>0.00000000000000000e+00</item>
			<item>0.00000000000000000e+00</item>
			<item>0.00000000000000000e+00</item>
			<item>0.00000000000000000e+00</item>
			<item>0.00000000000000000e+00</item>
		</item>
		<item>
			<n_rows>29</n_rows>
			<n_cols>1</n_cols>
			<n_elem>29</n_elem>
			<vec_state>1</vec_state>
			<item>0.00000000000000000e+00</item>
			<item>0.00000000000000000e+00</item>
			<item>0.00000000000000000e+00</item>
			<item>0.00000000000000000e+00</item>
			<item>-1.33171980100565468e-01</item>
			<item>-2.63466864530581824e-01</item>
			<item>-6.72582154442593894e-02</item>
			<item>-6.83021412235469139e-02</item>
			<item>0.00000000000000000e+00</item>
			<item>0.00000000000000000e+00</item>
			<item>0.00000000000000000e+00</item>
			<item>1.86442210480463333e-02</item>
			<item>0.00000000000000000e+00</item>
			<item>5.00322061474193780e-02</item>
			<item>8.77339375539402666e-02</item>
			<item>0.00000000000000000e+00</item>
			<item>0.00000000000000000e+00</item>
			<item>0.00000000000000000e+00</item>
			<item>0.00000000000000000e+00</item>
			<item>0.00000000000000000e+00</item>
			<item>0.00000000000000000e+00</item>
			<item>0.00000000000000000e+00</item>
			<item>0.00000000000000000e+00</item>
			<item>0.00000000000000000e+00</item>
			<item>0.00000000000000000e+00</item>
			<item>0.00000000000000000e+00</item>
			<item>0.00000000000000000e+00</item>
			<item>0.00000000000000000e+00</item>
			<item>0.00000000000000000e+00</item>
		</item>
		<item>
			<n_rows>29</n_rows>
			<n_cols>1</n_cols>
			<n_elem>29</n_elem>
			<vec_state>1</vec_state>
			<item>0.00000000000000000e+00</item>
			<item>0.00000000000000000e+00</item>
			<item>0.00000000000000000e+00</item>
			<item>0.00000000000000000e+00</item>
			<item>-1.33201322318331317e-01</item>
			<item>-2.63636045118393725e-01</item>
			<item>-7.69563719353349301e-02</item>
			<item>-8.17845670925491514e-02</item>
			<item>0.00000000000000000e+00</item>
			<item>0.00000000000000000e+00</item>
			<item>0.00000000000000000e+00</item>
			<item>5.73282998232546512e-02</item>
			<item>0.00000000000000000e+00</item>
			<item>7.96755761300237952e-02</item>
			<item>1.48120283401676434e-01</item>
			<item>0.00000000000000000e+00</item>
			<item>5.30402039902600417e-02</item>
			<item>0.00000000000000000e+00</item>
			<item>0.00000000000000000e+00</item>
			<item>0.00000000000000000e+00</item>
			<item>0.00000000000000000e+00</item>
			<item>0.00000000000000000e+00</item>
			<item>0.00000000000000000e+00</item>
			<item>0.00000000000000000e+00</item>
			<item>0.00000000000000000e+00</item>
			<item>0.00000000000000000e+00</item>
			<item>0.00000000000000000e+00</item>
			<item>0.00000000000000000e+00</item>
			<item>0.00000000000000000e+00</item>
		</item>
		<item>
			<n_rows>29</n_rows>
			<n_cols>1</n_cols>
			<n_elem>29</n_elem>
			<vec_state>1</vec_state>
			<item>0.00000000000000000e+00</item>
			<item>0.00000000000000000e+00</item>
			<item>0.00000000000000000e+00</item>
			<item>0.00000000000000000e+00</item>
			<item>-1.33271355343132947e-01</item>
			<item>-2.64291027353024510e-01</item>
			<item>-7.93856146383354055e-02</item>
			<item>-8.62383957539330642e-02</item>
			<item>0.00000000000000000e+00</item>
			<item>0.00000000000000000e+00</item>
			<item>0.00000000000000000e+00</item>
			<item>7.47843646571090398e-02</item>
			<item>-2.01590926990259968e-02</item>
			<item>9.41555346294046386e-02</item>
			<item>1.73312534917975519e-01</item>
			<item>0.00000000000000000e+00</item>
			<item>6.94108987235679542e-02</item>
			<item>0.00000000000000000e+00</item>
			<item>0.00000000000000000e+00</item>
			<item>0.00000000000000000e+00</item>
			<item>0.00000000000000000e+00</item>
			<item>0.00000000000000000e+00</item>
			<item>0.00000000000000000e+00</item>
			<item>0.00000000000000000e+00</item>
			<item>0.00000000000000000e+00</item>
			<item>0.00000000000000000e+00</item>
			<item>0.00000000000000000e+00</item>
			<item>0.00000000000000000e+00</item>
			<item>0.00000000000000000e+00</item>
		</item>
		<item>
			<n_rows>29</n_rows>
			<n_cols>1</n_cols>
			<n_elem>29</n_elem>
			<vec_state>1</vec_state>
			<item>0.00000000000000000e+00</item>
			<item>0.00000000000000000e+00</item>
			<item>0.00000000000000000e+00</item>
			<item>0.00000000000000000e+00</item>
			<item>-1.33636369005139255e-01</item>
			<item>-2.67908765393055637e-01</item>
			<item>-8.84338756412007820e-02</item>
			<item>-1.00596481324349923e-01</item>
			<item>0.00000000000000000e+00</item>
			<item>0.00000000000000000e+00</item>
			<item>-6.00546196965718315e-02</item>
			<item>1.48782003033181343e-01</item>
			<item>-9.67890342187792130e-02</item>
			<item>1.52072506585896494e-01</item>
			<item>2.72565680010650957e-01</item>
			<item>0.00000000000000000e+00</item>
			<item>1.50297848795156619e-01</item>
			<item>0.00000000000000000e+00</item>
			<item>0.00000000000000000e+00</item>
			<item>0.00000000000000000e+00</item>
			<item>0.00000000000000000e+00</item>
			<item>0.00000000000000000e+00</item>
			<item>0.00000000000000000e+00</item>
			<item>0.00000000000000000e+00</item>
			<item>0.00000000000000000e+00</item>
			<item>0.00000000000000000e+00</item>
			<item>0.00000000000000000e+00</item>
			<item>0.00000000000000000e+00</item>
			<item>0.00000000000000000e+00</item>
		</item>
		<item>
			<n_rows>29</n_rows>
			<n_cols>1</n_cols>
			<n_elem>29</n_elem>
			<vec_state>1</vec_state>
			<item>0.00000000000000000e+00</item>
			<item>0.00000000000000000e+00</item>
			<item>0.00000000000000000e+00</item>
			<item>0.00000000000000000e+00</item>
			<item>-1.33977950208032659e-01</item>
			<item>-2.70542898668895859e-01</item>
			<item>-9.09065114975359245e-02</item>
			<item>-1.12632740350634558e-01</item>
			<item>-3.02856903236749415e-02</item>
			<item>0.00000000000000000e+00</item>
			<item>-9.30384776482763437e-02</item>
			<item>1.99354815504432792e-01</item>
			<item>-1.55943508820231974e-01</item>
			<item>2.01794027204911186e-01</item>
			<item>3.46942415116983316e-01</item>
			<item>0.00000000000000000e+00</item>
			<item>2.16247458939017839e-01</item>
			<item>0.00000000000000000e+00</item>
			<item>0.00000000000000000e+00</item>
			<item>0.00000000000000000e+00</item>
			<item>0.00000000000000000e+00</item>
			<item>0.00000000000000000e+00</item>
			<item>0.00000000000000000e+00</item>
			<item>0.00000000000000000e+00</item>
			<item>0.00000000000000000e+00</item>
			<item>0.00000000000000000e+00</item>
			<item>0.00000000000000000e+00</item>
			<item>0.00000000000000000e+00</item>
			<item>0.00000000000000000e+00</item>
		</item>
		<item>
			<n_rows>29</n_rows>
			<n_cols>1</n_cols>
			<n_elem>29</n_elem>
			<vec_state>1</vec_state>
			<item>0.00000000000000000e+00</item>
			<item>0.00000000000000000e+00</item>
			<item>8.96273093828112044e-01</item>
			<item>0.00000000000000000e+00</item>
			<item>-1.31441053582175005e-01</item>
			<item>-2.58813205843071437e-01</item>
			<item>-7.86753149952606479e-02</item>
			<item>-1.13093992309326319e-01</item>
			<item>-3.22503505098944293e-02</item>
			<item>0.00000000000000000e+00</item>
			<item>-9.90311455829922666e-02</item>
			<item>2.23549470659562710e-01</item>
			<item>-1.66427950762829679e-01</item>
			<item>2.25747471414034673e-01</item>
			<item>3.64219927241387631e-01</item>
			<item>0.00000000000000000e+00</item>
			<item>2.44832963813547771e-01</item>
			<item>0.00000000000000000e+00</item>
			<item>0.00000000000000000e+00</item>
			<item>0.00000000000000000e+00</item>
			<item>0.00000000000000000e+00</item>
			<item>0.00000000000000000e+00</item>
			<item>0.00000000000000000e+00</item>
			<item>0.00000000000000000e+00</item>
			<item>0.00000000000000000e+00</item>
			<item>0.00000000000000000e+00</item>
			<item>0.00000000000000000e+00</item>
			<item>0.00000000000000000e+00</item>
			<item>0.00000000000000000e+00</item>
		</item>
		<item>
			<n_rows>29</n_rows>
			<n_cols>1</n_cols>
			<n_elem>29</n_elem>
			<vec_state>1</vec_state>
			<item>0.00000000000000000e+00</item>
			<item>0.00000000000000000e+00</item>
			<item>1.86691319847459747e+00</item>
			<item>0.00000000000000000e+00</item>
			<item>-1.28747312763148658e-01</item>
			<item>-2.46437362907271834e-01</item>
			<item>-6.54369184963494860e-02</item>
			<item>-1.13543363309258766e-01</item>
			<item>-3.47876287176381790e-02</item>
			<item>0.00000000000000000e+00</item>
			<item>-1.04634835779902749e-01</item>
			<item>2.50601242054679096e-01</item>
			<item>-1.78242175540391873e-01</item>
			<item>2.50741697143611886e-01</item>
			<item>3.86302110723634462e-01</item>
			<item>-1.49244703097304657e-02</item>
			<item>2.79352658020714739e-01</item>
			<item>0.00000000000000000e+00</item>
			<item>0.00000000000000000e+00</item>
			<item>0.00000000000000000e+00</item>
			<item>0.00000000000000000e+00</item>
			<item>0.00000000000000000e+00</item>
			<item>0.00000000000000000e+00</item>
			<item>0.00000000000000000e+00</item>
			<item>0.00000000000000000e+00</item>
			<item>0.00000000000000000e+00</item>
			<item>0.00000000000000000e+00</item>
			<item>0.00000000000000000e+00</item>
			<item>0.00000000000000000e+00</item>
		</item>
		<item>
			<n_rows>29</n_rows>
			<n_cols>1</n_cols>
			<n_elem>29</n_elem>
			<vec_state>1</vec_state>
			<item>0.00000000000000000e+00</item>
			<item>0.00000000000000000e+00</item>
			<item>2.51794457357617230e+00</item>
			<item>0.00000000000000000e+00</item>
			<item>-1.26732776763332666e-01</item>
			<item>-2.37495807616261073e-01</item>
			<item>-5.72236506156023686e-02</item>
			<item>-1.13893589191295483e-01</item>
			<item>-3.60211261858572329e-02</item>
			<item>1.95834665355827907e-02</item>
			<item>-1.07641471782563183e-01</item>
			<item>2.67204811570136369e-01</item>
			<item>-1.86850829864469631e-01</item>
			<item>2.69624746335226206e-01</item>
			<item>3.95821440981490746e-01</item>
			<item>-2.48152282985518099e-02</item>
			<item>3.04870609688680627e-01</item>
			<item>0.00000000000000000e+00</item>
			<item>0.00000000000000000e+00</item>
			<item>0.00000000000000000e+00</item>
			<item>0.00000000000000000e+00</item>
			<item>0.00000000000000000e+00</item>
			<item>0.00000000000000000e+00</item>
			<item>0.00000000000000000e+00</item>
			<item>0.00000000000000000e+00</item>
			<item>0.00000000000000000e+00</item>
			<item>0.00000000000000000e+00</item>
			<item>0.00000000000000000e+00</item>
			<item>0.00000000000000000e+00</item>
		</item>
		<item>
			<n_rows>29</n_rows>
			<n_cols>1</n_cols>
			<n_elem>29</n_elem>
			<vec_state>1</vec_state>
			<item>1.93584790222847474e+01</item>
			<item>0.00000000000000000e+00</item>
			<item>-9.68583819897094411e-01</item>
			<item>0.00000000000000000e+00</item>
			<item>-9.98205756348778256e-02</item>
			<item>-1.38883301128508496e-01</item>
			<item>-2.44478389660003764e-02</item>
			<item>-4.01732608753279236e-02</item>
			<item>-5.60806324679241630e-03</item>
			<item>1.88579105860492646e-01</item>
			<item>-1.34451194770400184e-01</item>
			<item>3.64815158565749587e-01</item>
			<item>-2.19391788348275774e-01</item>
			<item>3.78334384081032260e-01</item>
			<item>3.67375565445466123e-01</item>
			<item>-1.46211475284446779e-03</item>
			<item>3.46375750031262308e-01</item>
			<item>0.00000000000000000e+00</item>
			<item>0.00000000000000000e+00</item>
			<item>0.00000000000000000e+00</item>
			<item>0.00000000000000000e+00</item>
			<item>0.00000000000000000e+00</item>
			<item>0.00000000000000000e+00</item>
			<item>0.00000000000000000e+00</item>
			<item>0.00000000000000000e+00</item>
			<item>0.00000000000000000e+00</item>
			<item>0.00000000000000000e+00</item>
			<item>0.00000000000000000e+00</item>
			<item>0.00000000000000000e+00</item>
		</item>
		<item>
			<n_rows>29</n_rows>
			<n_cols>1</n_cols>
			<n_elem>29</n_elem>
			<vec_state>1</vec_state>
			<item>2.29432488223083908e+01</item>
			<item>0.00000000000000000e+00</item>
			<item>-1.66363576470094476e+00</item>
			<item>7.62327966734525519e-01</item>
			<item>-9.44608267768186072e-02</item>
			<item>-1.22913052096678216e-01</item>
			<item>-1.68963113504977044e-02</item>
			<item>-2.76685557524764328e-02</item>
			<item>-2.07789116932760110e-03</item>
			<item>2.20385892136291228e-01</item>
			<item>-1.39346062212397287e-01</item>
			<item>3.84076798761923355e-01</item>
			<item>-2.22934176071549778e-01</item>
			<item>3.92806811825528013e-01</item>
			<item>3.65842341731278109e-01</item>
			<item>-2.44219402999449296e-03</item>
			<item>3.58205459316013830e-01</item>
			<item>0.00000000000000000e+00</item>
			<item>0.00000000000000000e+00</item>
			<item>0.00000000000000000e+00</item>
			<item>0.00000000000000000e+00</item>
			<item>0.00000000000000000e+00</item>
			<item>0.00000000000000000e+00</item>
			<item>0.00000000000000000e+00</item>
			<item>0.00000000000000000e+00</item>
			<item>0.00000000000000000e+00</item>
			<item>0.00000000000000000e+00</item>
			<item>0.00000000000000000e+00</item>
			<item>0.00000000000000000e+00</item>
		</item>
		<item>
			<n_rows>29</n_rows>
			<n_cols>1</n_cols>
			<n_elem>29</n_elem>
			<vec_state>1</vec_state>
			<item>2.43092644537690852e+01</item>
			<item>-4.23486480628232087e+00</item>
			<item>-9.53892898680188783e-01</item>
			<item>7.71187306727097677e-01</item>
			<item>-9.47487342507192659e-02</item>
			<item>-1.22103907476607529e-01</item>
			<item>-2.36746938223500354e-02</item>
			<item>-3.04204328950538685e-02</item>
			<item>-9.56438341016093915e-03</item>
			<item>2.17476631300019957e-01</item>
			<item>-1.43756677279108736e-01</item>
			<item>3.81517346780763600e-01</item>
			<item>-2.25734107247859889e-01</item>
			<item>3.86324769956449321e-01</item>
			<item>3.55338192112534756e-01</item>
			<item>2.23059947120245790e-03</item>
			<item>3.52229345341921740e-01</item>
			<item>0.00000000000000000e+00</item>
			<item>0.00000000000000000e+00</item>
			<item>0.00000000000000000e+00</item>
			<item>0.00000000000000000e+00</item>
			<item>0.00000000000000000e+00</item>
			<item>0.00000000000000000e+00</item>
			<item>0.00000000000000000e+00</item>
			<item>0.00000000000000000e+00</item>
			<item>0.00000000000000000e+00</item>
			<item>0.00000000000000000e+00</item>
			<item>0.00000000000000000e+00</item>
			<item>0.00000000000000000e+00</item>
		</item>
		<item>
			<n_rows>29</n_rows>
			<n_cols>1</n_cols>
			<n_elem>29</n_elem>
			<vec_state>1</vec_state>
			<item>2.41295148881220811e+01</item>
			<item>-4.18920585929721323e+00</item>
			<item>-1.02967077678482810e+00</item>
			<item>5.31941471875027272e-01</item>
			<item>-9.46627739436119303e-02</item>
			<item>-1.21820702576302634e-01</item>
			<item>-2.36819508558899980e-02</item>
			<item>-3.10844781968228345e-02</item>
			<item>-1.35719596100820333e-02</item>
			<item>2.18066025603400437e-01</item>
			<item>-1.46148686532026367e-01</item>
			<item>3.82285008779014113e-01</item>
			<item>-2.33318687282020570e-01</item>
			<item>3.84560349702593229e-01</item>
			<item>3.42939334034737253e-01</item>
			<item>-7.69191685393821444e-03</item>
			<item>3.55784538913999859e-01</item>
			<item>0.00000000000000000e+00</item>
			<item>0.00000000000000000e+00</item>
			<item>0.00000000000000000e+00</item>
			<item>0.00000000000000000e+00</item>
			<item>0.00000000000000000e+00</item>
			<item>0.00000000000000000e+00</item>
			<item>0.00000000000000000e+00</item>
			<item>1.44321874254446612e+02</item>
			<item>0.00000000000000000e+00</item>
			<item>0.00000000000000000e+00</item>
			<item>0.00000000000000000e+00</item>
			<item>0.00000000000000000e+00</item>
		</item>
		<item>
			<n_rows>29</n_rows>
			<n_cols>1</n_cols>
			<n_elem>29</n_elem>
			<vec_state>1</vec_state>
			<item>2.39080464505326589e+01</item>
			<item>-4.02411219147881294e+00</item>
			<item>-1.19098816306210775e+00</item>
			<item>3.17394281255357513e-01</item>
			<item>-9.47103706013658203e-02</item>
			<item>-1.22301432536549640e-01</item>
			<item>-2.51994372498674166e-02</item>
			<item>-3.11835178210338772e-02</item>
			<item>-1.89463545452818113e-02</item>
			<item>2.15603221461262901e-01</item>
			<item>-1.50968514058955838e-01</item>
			<item>3.77562969437569784e-01</item>
			<item>-2.43267831971390541e-01</item>
			<item>3.83639739711572225e-01</item>
			<item>3.37328433218521739e-01</item>
			<item>-8.61807907434630760e-03</item>
			<item>3.57222167735524898e-01</item>
			<item>0.00000000000000000e+00</item>
			<item>0.00000000000000000e+00</item>
			<item>0.00000000000000000e+00</item>
			<item>0.00000000000000000e+00</item>
			<item>0.00000000000000000e+00</item>
			<item>0.00000000000000000e+00</item>
			<item>0.00000000000000000e+00</item>
			<item>1.66203296092707603e+02</item>
			<item>0.00000000000000000e+00</item>
			<item>1.41246583845364597e+02</item>
			<item>0.00000000000000000e+00</item>
			<item>0.00000000000000000e+00</item>
		</item>
		<item>
			<n_rows>29</n_rows>
			<n_cols>1</n_cols>
			<n_elem>29</n_elem>
			<vec_state>1</vec_state>
			<item>2.37507829608984125e+01</item>
			<item>-3.98514745024696770e+00</item>
			<item>-1.28691565725504264e+00</item>
			<item>1.78755661551690870e-01</item>
			<item>-9.47564268931331000e-02</item>
			<item>-1.22820660760381395e-01</item>
			<item>-2.64709216940367635e-02</item>
			<item>-3.05834302237468006e-02</item>
			<item>-2.25797105566402749e-02</item>
			<item>2.13463296587147688e-01</item>
			<item>-1.54906120073952019e-01</item>
			<item>3.74706204587518688e-01</item>
			<item>-2.50441673808839915e-01</item>
			<item>3.83649980662007450e-01</item>
			<item>3.34156071527498100e-01</item>
			<item>-8.49132735140895045e-03</item>
			<item>3.56368717021686876e-01</item>
			<item>0.00000000000000000e+00</item>
			<item>0.00000000000000000e+00</item>
			<item>4.42982163375295599e+01</item>
			<item>0.00000000000000000e+00</item>
			<item>0.00000000000000000e+00</item>
			<item>0.00000000000000000e+00</item>
			<item>0.00000000000000000e+00</item>
			<item>1.61521757105104655e+02</item>
			<item>0.00000000000000000e+00</item>
			<item>2.18623766267851607e+02</item>
			<item>0.00000000000000000e+00</item>
			<item>0.00000000000000000e+00</item>
		</item>
		<item>
			<n_rows>29</n_rows>
			<n_cols>1</n_cols>
			<n_elem>29</n_elem>
			<vec_state>1</vec_state>
			<item>2.34638212583533559e+01</item>
			<item>-3.99028732828248556e+00</item>
			<item>-1.41871762610930219e+00</item>
			<item>-1.15304814507461328e-01</item>
			<item>-9.47796108697570444e-02</item>
			<item>-1.23356903171044668e-01</item>
			<item>-2.87915288794361214e-02</item>
			<item>-2.93715751638949918e-02</item>
			<item>-2.84984475845668911e-02</item>
			<item>2.08669213047292718e-01</item>
			<item>-1.63241273082257110e-01</item>
			<item>3.69038213899133771e-01</item>
			<item>-2.61075673086592963e-01</item>
			<item>3.83710909824851620e-01</item>
			<item>3.24840951359968766e-01</item>
			<item>-9.46759004926097693e-03</item>
			<item>3.53433568811274579e-01</item>
			<item>0.00000000000000000e+00</item>
			<item>0.00000000000000000e+00</item>
			<item>1.13720188441650095e+02</item>
			<item>0.00000000000000000e+00</item>
			<item>0.00000000000000000e+00</item>
			<item>5.05358225302097921e+01</item>
			<item>0.00000000000000000e+00</item>
			<item>1.40752475777027968e+02</item>
			<item>0.00000000000000000e+00</item>
			<item>3.42829996209040758e+02</item>
			<item>0.00000000000000000e+00</item>
			<item>0.00000000000000000e+00</item>
		</item>
		<item>
			<n_rows>29</n_rows>
			<n_cols>1</n_cols>
			<n_elem>29</n_elem>
			<vec_state>1</vec_state>
			<item>2.23629633312655614e+01</item>
			<item>-3.87691745204716431e+00</item>
			<item>-1.68678086208373523e+00</item>
			<item>-1.01139350348178914e+00</item>
			<item>-9.50944281175582634e-02</item>
			<item>-1.25185624288743330e-01</item>
			<item>-4.00006580212139556e-02</item>
			<item>-2.50365127838725644e-02</item>
			<item>-3.91058928613480933e-02</item>
			<item>1.92645675248152737e-01</item>
			<item>-1.89852339664791814e-01</item>
			<item>3.51977017907799006e-01</item>
			<item>-2.88425665057965908e-01</item>
			<item>3.87061209757030844e-01</item>
			<item>3.16696077994148839e-01</item>
			<item>-9.37192014099686235e-03</item>
			<item>3.34030912171883687e-01</item>
			<item>0.00000000000000000e+00</item>
			<item>0.00000000000000000e+00</item>
			<item>2.29512690854313917e+02</item>
			<item>0.00000000000000000e+00</item>
			<item>0.00000000000000000e+00</item>
			<item>1.27454545632835988e+02</item>
			<item>0.00000000000000000e+00</item>
			<item>2.78700811736855769e+01</item>
			<item>0.00000000000000000e+00</item>
			<item>5.30500842350461880e+02</item>
			<item>0.00000000000000000e+00</item>
			<item>3.49930247260577119e+02</item>
		</item>
		<item>
			<n_rows>29</n_rows>
			<n_cols>1</n_cols>
			<n_elem>29</n_elem>
			<vec_state>1</vec_state>
			<item>2.21339335535931667e+01</item>
			<item>-3.93955418009082381e+00</item>
			<item>-1.65724964255997786e+00</item>
			<item>-1.08734482140148825e+00</item>
			<item>-9.51860190789255295e-02</item>
			<item>-1.25703571442999207e-01</item>
			<item>-4.26877496434525869e-02</item>
			<item>-2.40638839771277480e-02</item>
			<item>-3.72944893925475848e-02</item>
			<item>1.91887382325122285e-01</item>
			<item>-1.92152633271290479e-01</item>
			<item>3.52684174612941603e-01</item>
			<item>-2.91540498194402975e-01</item>
			<item>3.89795245274908719e-01</item>
			<item>3.18513330468259526e-01</item>
			<item>-9.41227944455085008e-03</item>
			<item>3.28781949065015899e-01</item>
			<item>0.00000000000000000e+00</item>
			<item>0.00000000000000000e+00</item>
			<item>2.34117644873579849e+02</item>
			<item>0.00000000000000000e+00</item>
			<item>0.00000000000000000e+00</item>
			<item>1.81484852765253578e+02</item>
			<item>0.00000000000000000e+00</item>
			<item>2.50923688874962281e+00</item>
			<item>0.00000000000000000e+00</item>
			<item>6.22730665530170199e+02</item>
			<item>-1.67468374441407775e+02</item>
			<item>4.76051245895182205e+02</item>
		</item>
		<item>
			<n_rows>29</n_rows>
			<n_cols>1</n_cols>
			<n_elem>29</n_elem>
			<vec_state>1</vec_state>
			<item>2.21164759054333047e+01</item>
			<item>-3.96576891690688615e+00</item>
			<item>-1.65304697445888693e+00</item>
			<item>-1.08550668184613675e+00</item>
			<item>-9.52046299500093618e-02</item>
			<item>-1.25820517816965904e-01</item>
			<item>-4.29794171665296640e-02</item>
			<item>-2.40878221017014407e-02</item>
			<item>-3.71515487762744956e-02</item>
			<item>1.91672567532649857e-01</item>
			<item>-1.92233698988592716e-01</item>
			<item>3.52766214707009251e-01</item>
			<item>-2.91933367691672552e-01</item>
			<item>3.90229111337799472e-01</item>
			<item>3.18617172852314778e-01</item>
			<item>-9.32005593475778576e-03</item>
			<item>3.28196287630540595e-01</item>
			<item>0.00000000000000000e+00</item>
			<item>0.00000000000000000e+00</item>
			<item>2.41925858204109460e+02</item>
			<item>-1.40398374424712493e+01</item>
			<item>0.00000000000000000e+00</item>
			<item>1.90988021448736760e+02</item>
			<item>0.00000000000000000e+00</item>
			<item>1.51031321030784937e+00</item>
			<item>0.00000000000000000e+00</item>
			<item>6.30927663791431996e+02</item>
			<item>-1.84015247259199953e+02</item>
			<item>4.89322504755403656e+02</item>
		</item>
		<item>
			<n_rows>29</n_rows>
			<n_cols>1</n_cols>
			<n_elem>29</n_elem>
			<vec_state>1</vec_state>
			<item>2.19457833062955601e+01</item>
			<item>-4.13072472078025843e+00</item>
			<item>-1.60943513643052794e+00</item>
			<item>-1.07235713315984516e+00</item>
			<item>-9.53281336147774050e-02</item>
			<item>-1.26596363459227979e-01</item>
			<item>-4.50124381963476622e-02</item>
			<item>-2.42308153928745447e-02</item>
			<item>-3.62121040318413648e-02</item>
			<item>1.90357643069770793e-01</item>
			<item>-1.92825025980842141e-01</item>
			<item>3.53462632459062454e-01</item>
			<item>-2.94878460925339425e-01</item>
			<item>3.93728302076321313e-01</item>
			<item>3.19529311992660658e-01</item>
			<item>-8.52599519501940489e-03</item>
			<item>3.23727275021434113e-01</item>
			<item>0.00000000000000000e+00</item>
			<item>0.00000000000000000e+00</item>
			<item>3.02758232183150824e+02</item>
			<item>-1.22900083450904901e+02</item>
			<item>0.00000000000000000e+00</item>
			<item>2.54084766196461771e+02</item>
			<item>2.47177435400563823e+01</item>
			<item>-1.19697128560814949e+01</item>
			<item>0.00000000000000000e+00</item>
			<item>6.89297684918628079e+02</item>
			<item>-3.09168446356678885e+02</item>
			<item>5.87119318096956704e+02</item>
		</item>
		<item>
			<n_rows>29</n_rows>
			<n_cols>1</n_cols>
			<n_elem>29</n_elem>
			<vec_state>1</vec_state>
			<item>2.19498733196439275e+01</item>
			<item>-4.29029492997693929e+00</item>
			<item>-1.57433027440372242e+00</item>
			<item>-1.10812725188973671e+00</item>
			<item>-9.53743042078795678e-02</item>
			<item>-1.26748018953890818e-01</item>
			<item>-4.69343545820500307e-02</item>
			<item>-2.42291232880294909e-02</item>
			<item>-3.51269041112479904e-02</item>
			<item>1.89282907810052442e-01</item>
			<item>-1.92741098203788208e-01</item>
			<item>3.55463345493531813e-01</item>
			<item>-2.93344598938272139e-01</item>
			<item>3.93802181217643710e-01</item>
			<item>3.19934904307084544e-01</item>
			<item>-1.13567840201177182e-02</item>
			<item>3.22479135006152773e-01</item>
			<item>-7.48487104719656600e+01</item>
			<item>0.00000000000000000e+00</item>
			<item>3.46077143108317273e+02</item>
			<item>-1.68895442512351138e+02</item>
			<item>0.00000000000000000e+00</item>
			<item>3.07153572528612870e+02</item>
			<item>1.43316910553567833e+01</item>
			<item>7.74730678719209997e+00</item>
			<item>0.00000000000000000e+00</item>
			<item>7.04693115197959173e+02</item>
			<item>-3.73989369889586328e+02</item>
			<item>6.78910755842628191e+02</item>
		</item>
		<item>
			<n_rows>29</n_rows>
			<n_cols>1</n_cols>
			<n_elem>29</n_elem>
			<vec_state>1</vec_state>
			<item>2.18049998456458560e+01</item>
			<item>-4.67139584129927066e+00</item>
			<item>-1.46964317299906688e+00</item>
			<item>-1.17984758585067717e+00</item>
			<item>-9.56444388168470050e-02</item>
			<item>-1.28196934255007111e-01</item>
			<item>-5.22122635259774370e-02</item>
			<item>-2.37969175246216490e-02</item>
			<item>-3.21668242987657657e-02</item>
			<item>1.85422246516687844e-01</item>
			<item>-1.92379997745911913e-01</item>
			<item>3.67515263081286792e-01</item>
			<item>-2.87932223044140567e-01</item>
			<item>3.91336079372270218e-01</item>
			<item>3.12280864350099385e-01</item>
			<item>-1.91735261519876826e-02</item>
			<item>3.20321887506681280e-01</item>
			<item>-2.98576266274960972e+02</item>
			<item>0.00000000000000000e+00</item>
			<item>4.18979479990465336e+02</item>
			<item>-1.68724688383476916e+02</item>
			<item>-3.69150215787300453e+02</item>
			<item>5.95550604677891897e+02</item>
			<item>-6.45253811083186157e+00</item>
			<item>5.66831413116611174e+01</item>
			<item>0.00000000000000000e+00</item>
			<item>8.01812920242703399e+02</item>
			<item>-6.13854206205925038e+02</item>
			<item>1.08907219942794609e+03</item>
		</item>
		<item>
			<n_rows>29</n_rows>
			<n_cols>1</n_cols>
			<n_elem>29</n_elem>
			<vec_state>1</vec_state>
			<item>2.18034313916215474e+01</item>
			<item>-4.67653880023475033e+00</item>
			<item>-1.46885368287115448e+00</item>
			<item>-1.18107648299517209e+00</item>
			<item>-9.56498042670750614e-02</item>
			<item>-1.28225472983957950e-01</item>
			<item>-5.22898867648211585e-02</item>
			<item>-2.38056786721136775e-02</item>
			<item>-3.21738378595328028e-02</item>
			<item>1.85356550048390412e-01</item>
			<item>-1.92374084283118557e-01</item>
			<item>3.67613578667078833e-01</item>
			<item>-2.87886282281673289e-01</item>
			<item>3.91313372893241973e-01</item>
			<item>3.12132776161116121e-01</item>
			<item>-1.92685474049605135e-02</item>
			<item>3.20334316653995643e-01</item>
			<item>-3.02368638672404416e+02</item>
			<item>2.02163413026494920e+00</item>
			<item>4.19104255654732071e+02</item>
			<item>-1.68419076409519874e+02</item>
			<item>-3.74183267952843437e+02</item>
			<item>5.99743262515653328e+02</item>
			<item>-7.53002173330255520e+00</item>
			<item>5.77202605911775208e+01</item>
			<item>0.00000000000000000e+00</item>
			<item>8.03032682734563309e+02</item>
			<item>-6.17205653981585101e+02</item>
			<item>1.09457860492977557e+03</item>
		</item>
		<item>
			<n_rows>29</n_rows>
			<n_cols>1</n_cols>
			<n_elem>29</n_elem>
			<vec_state>1</vec_state>
			<item>2.17971844155485357e+01</item>
			<item>-4.73605000963253620e+00</item>
			<item>-1.50222054940464966e+00</item>
			<item>-1.20059170532117587e+00</item>
			<item>-9.58167606674452804e-02</item>
			<item>-1.29174968952348562e-01</item>
			<item>-5.41190649512799937e-02</item>
			<item>-2.39602711482502055e-02</item>
			<item>-3.23096178974786249e-02</item>
			<item>1.83559110149200899e-01</item>
			<item>-1.92405042047117975e-01</item>
			<item>3.69590126594064039e-01</item>
			<item>-2.86935253119040390e-01</item>
			<item>3.90538736498183159e-01</item>
			<item>3.09805123753574496e-01</item>
			<item>-2.03537643823777960e-02</item>
			<item>3.21073317493090815e-01</item>
			<item>-3.89490063472898669e+02</item>
			<item>7.15546423216561465e+01</item>
			<item>3.88352807806141186e+02</item>
			<item>-1.35010942070620388e+02</item>
			<item>-5.04188295910232114e+02</item>
			<item>7.00698243436327061e+02</item>
			<item>-3.72310021132709892e+01</item>
			<item>1.20580589344427068e+02</item>
			<item>-8.41904840374459837e+01</item>
			<item>8.68030258202560958e+02</item>
			<item>-6.97883393904128980e+02</item>
			<item>1.21813145151129584e+03</item>
		</item>
	</betaPath>
	<lambdaPath>
		<count>30</count>
		<item_version>0</item_version>
		<item>1.21863906097983607e+05</item>
		<item>6.80357469733164180e+02</item>
		<item>4.90021578233636319e+01</item>
		<item>3.52645926520031594e+01</item>
		<item>2.20749849346226483e+01</item>
		<item>2.18786371266322028e+01</item>
		<item>1.93610911066870734e+01</item>
		<item>1.78105107126367308e+01</item>
		<item>1.46280954507639702e+01</item>
		<item>1.34398957659793687e+01</item>
		<item>8.84318025857454160e+00</item>
		<item>5.62424093006304204e+00</item>
		<item>4.60504753712254722e+00</item>
		<item>3.48535622580380045e+00</item>
		<item>2.78384933026792103e+00</item>
		<item>5.12610185608073698e-01</item>
		<item>7.61273179578902948e-02</item>
		<item>3.41528739364265962e-02</item>
		<item>2.80009823475329718e-02</item>
		<item>2.38170411734738192e-02</item>
		<item>2.10379303851692713e-02</item>
		<item>1.59477519172149529e-02</item>
		<item>3.63408592203254017e-03</item>
		<item>2.58300225310012640e-03</item>
		<item>2.46422320232255604e-03</item>
		<item>1.56111866301580134e-03</item>
		<item>1.16320499715375164e-03</item>
		<item>2.65255280951830967e-04</item>
		<item>2.53359036599230196e-04</item>
		<item>2.33604132206770710e-12</item>
	</lambdaPath>
	<activeSet>
		<count>29</count>
		<item_version>0</item_version>
		<item>4</item>
		<item>5</item>
		<item>6</item>
		<item>7</item>
		<item>13</item>
		<item>14</item>
		<item>11</item>
		<item>16</item>
		<item>12</item>
		<item>10</item>
		<item>8</item>
		<item>2</item>
		<item>15</item>
		<item>9</item>
		<item>0</item>
		<item>3</item>
		<item>1</item>
		<item>24</item>
		<item>26</item>
		<item>19</item>
		<item>22</item>
		<item>28</item>
		<item>27</item>
		<item>20</item>
		<item>23</item>
		<item>17</item>
		<item>21</item>
		<item>18</item>
		<item>25</item>
	</activeSet>
	<isActive>
		<count>29</count>
		<item>1</item>
		<item>1</item>
		<item>1</item>
		<item>1</item>
		<item>1</item>
		<item>1</item>
		<item>1</item>
		<item>1</item>
		<item>1</item>
		<item>1</item>
		<item>1</item>
		<item>1</item>
		<item>1</item>
		<item>1</item>
		<item>1</item>
		<item>1</item>
		<item>1</item>
		<item>1</item>
		<item>1</item>
		<item>1</item>
		<item>1</item>
		<item>1</item>
		<item>1</item>
		<item>1</item>
		<item>1</item>
		<item>1</item>
		<item>1</item>
		<item>1</item>
		<item>1</item>
	</isActive>
	<ignoreSet>
		<count>0</count>
		<item_version>0</item_version>
	</ignoreSet>
	<isIgnored>
		<count>29</count>
		<item>0</item>
		<item>0</item>
		<item>0</item>
		<item>0</item>
		<item>0</item>
		<item>0</item>
		<item>0</item>
		<item>0</item>
		<item>0</item>
		<item>0</item>
		<item>0</item>
		<item>0</item>
		<item>0</item>
		<item>0</item>
		<item>0</item>
		<item>0</item>
		<item>0</item>
		<item>0</item>
		<item>0</item>
		<item>0</item>
		<item>0</item>
		<item>0</item>
		<item>0</item>
		<item>0</item>
		<item>0</item>
		<item>0</item>
		<item>0</item>
		<item>0</item>
		<item>0</item>
	</isIgnored>
</lars_model>
</boost_serialization>

